{
  "background": {
    "top": [
      0.08,
      0.04,
      0.15
    ],
    "bottom": [
      0.12,
      0.06,
      0.2
    ]
  },
  "camera": {
    "lookat": [
      0,
      2,
      0
    ],
    "up": [
      0,
      1,
      0
    ],
    "vfov": 50,
    "orbit": {
      "center": [
        0,
        2,
        0
      ],
      "radius": 12,
      "height": 4,
      "speed": 0.6,
      "phase": 0.8
    }
  },
  "materials": {
    "smooth_basalt": {
      "type": "glossy",
      "albedo": [
        0.15,
        0.14,
        0.16
      ],
      "specular": 0.2,
      "shininess": 16
    },
    "calcite": {
      "type": "glossy",
      "albedo": [
        0.85,
        0.83,
        0.8
      ],
      "specular": 0.35,
      "shininess": 24
    },
    "amethyst": {
      "type": "dielectric",
      "ior": 1.55,
      "albedo": [
        0.6,
        0.3,
        0.75
      ]
    },
    "amethyst_deep": {
      "type": "dielectric",
      "ior": 1.6,
      "albedo": [
        0.45,
        0.15,
        0.6
      ]
    },
    "amethyst_lite": {
      "type": "dielectric",
      "ior": 1.5,
      "albedo": [
        0.75,
        0.5,
        0.85
      ]
    },
    "crystal_glow": {
      "type": "emissive",
      "emission": [
        0.45,
        0.2,
        0.7
      ]
    },
    "crystal_glow2": {
      "type": "emissive",
      "emission": [
        0.3,
        0.15,
        0.55
      ]
    },
    "budding": {
      "type": "glossy",
      "albedo": [
        0.5,
        0.25,
        0.6
      ],
      "specular": 0.5,
      "shininess": 48
    },
    "cave_floor": {
      "type": "checkerboard",
      "albedo": [
        0.12,
        0.12,
        0.14
      ],
      "albedo2": [
        0.1,
        0.1,
        0.12
      ],
      "scale": 1.0
    },
    "tuff": {
      "type": "diffuse",
      "albedo": [
        0.35,
        0.35,
        0.3
      ]
    },
    "geode_shell": {
      "type": "glossy",
      "albedo": [
        0.2,
        0.2,
        0.22
      ],
      "specular": 0.15,
      "shininess": 10
    }
  },
  "objects": [
    {
      "type": "plane",
      "point": [
        0,
        0,
        0
      ],
      "normal": [
        0,
        1,
        0
      ],
      "material": "cave_floor"
    },
    {
      "type": "box",
      "center": [
        -4,
        1.0,
        -3
      ],
      "material": "smooth_basalt",
      "size": [
        3.0,
        3.0,
        3.0
      ]
    },
    {
      "type": "box",
      "center": [
        4,
        1.2,
        -3
      ],
      "material": "smooth_basalt",
      "size": [
        3.0,
        3.0,
        3.0
      ]
    },
    {
      "type": "box",
      "center": [
        -4,
        1.0,
        3
      ],
      "material": "geode_shell",
      "size": [
        2.6,
        2.6,
        2.6
      ]
    },
    {
      "type": "box",
      "center": [
        4,
        1.0,
        3
      ],
      "material": "geode_shell",
      "size": [
        2.6,
        2.6,
        2.6
      ]
    },
    {
      "type": "box",
      "center": [
        0,
        1.0,
        -4
      ],
      "material": "smooth_basalt",
      "size": [
        2.4,
        2.4,
        2.4
      ]
    },
    {
      "type": "box",
      "center": [
        -3.5,
        2.2,
        -2.5
      ],
      "material": "calcite",
      "size": [
        0.8,
        0.8,
        0.8
      ]
    },
    {
      "type": "box",
      "center": [
        3.5,
        2.2,
        -2.5
      ],
      "material": "calcite",
      "size": [
        0.8,
        0.8,
        0.8
      ]
    },
    {
      "type": "box",
      "center": [
        -3.5,
        2.0,
        2.5
      ],
      "material": "calcite",
      "size": [
        0.7,
        0.7,
        0.7
      ]
    },
    {
      "type": "box",
      "center": [
        0,
        0.6,
        0
      ],
      "material": "amethyst",
      "size": [
        1.2,
        1.2,
        1.2
      ]
    },
    {
      "type": "box",
      "center": [
        0,
        1.5,
        0
      ],
      "material": "amethyst_deep",
      "size": [
        0.8,
        0.8,
        0.8
      ]
    },
    {
      "type": "sphere",
      "center": [
        0,
        2.2,
        0
      ],
      "radius": 0.25,
      "material": "crystal_glow"
    },
    {
      "type": "triangle",
      "v0": [
        -0.3,
        0.8,
        -0.2
      ],
      "v1": [
        0.3,
        0.8,
        -0.2
      ],
      "v2": [
        0,
        2.5,
        0
      ],
      "material": "amethyst"
    },
    {
      "type": "triangle",
      "v0": [
        -0.2,
        0.8,
        0.3
      ],
      "v1": [
        0.2,
        0.8,
        0.3
      ],
      "v2": [
        0,
        2.5,
        0
      ],
      "material": "amethyst_lite"
    },
    {
      "type": "box",
      "center": [
        -2,
        0.4,
        -1
      ],
      "material": "amethyst_deep",
      "size": [
        0.8,
        0.8,
        0.8
      ]
    },
    {
      "type": "box",
      "center": [
        -2,
        1.0,
        -1
      ],
      "material": "amethyst",
      "size": [
        0.5,
        0.5,
        0.5
      ]
    },
    {
      "type": "sphere",
      "center": [
        -2,
        1.4,
        -1
      ],
      "radius": 0.15,
      "material": "crystal_glow2"
    },
    {
      "type": "triangle",
      "v0": [
        -2.2,
        0.5,
        -1.2
      ],
      "v1": [
        -1.8,
        0.5,
        -1.2
      ],
      "v2": [
        -2,
        1.6,
        -1
      ],
      "material": "amethyst_deep"
    },
    {
      "type": "box",
      "center": [
        2,
        0.35,
        1
      ],
      "material": "amethyst",
      "size": [
        0.7,
        0.7,
        0.7
      ]
    },
    {
      "type": "box",
      "center": [
        2,
        0.9,
        1
      ],
      "material": "amethyst_lite",
      "size": [
        0.44,
        0.44,
        0.44
      ]
    },
    {
      "type": "sphere",
      "center": [
        2,
        1.2,
        1
      ],
      "radius": 0.12,
      "material": "crystal_glow"
    },
    {
      "type": "triangle",
      "v0": [
        1.8,
        0.4,
        0.8
      ],
      "v1": [
        2.2,
        0.4,
        0.8
      ],
      "v2": [
        2,
        1.5,
        1
      ],
      "material": "amethyst"
    },
    {
      "type": "box",
      "center": [
        1,
        0.3,
        -2
      ],
      "material": "amethyst_deep",
      "size": [
        0.6,
        0.6,
        0.6
      ]
    },
    {
      "type": "sphere",
      "center": [
        1,
        0.7,
        -2
      ],
      "radius": 0.18,
      "material": "crystal_glow2"
    },
    {
      "type": "box",
      "center": [
        -1.5,
        0.25,
        2
      ],
      "material": "amethyst_lite",
      "size": [
        0.5,
        0.5,
        0.5
      ]
    },
    {
      "type": "sphere",
      "center": [
        -1.5,
        0.6,
        2
      ],
      "radius": 0.15,
      "material": "crystal_glow"
    },
    {
      "type": "box",
      "center": [
        3,
        0.2,
        -1
      ],
      "material": "budding",
      "size": [
        0.4,
        0.4,
        0.4
      ]
    },
    {
      "type": "box",
      "center": [
        -3,
        0.25,
        0
      ],
      "material": "budding",
      "size": [
        0.5,
        0.5,
        0.5
      ]
    },
    {
      "type": "box",
      "center": [
        0,
        0.2,
        3
      ],
      "material": "tuff",
      "size": [
        0.6,
        0.6,
        0.6
      ]
    },
    {
      "type": "box",
      "center": [
        2,
        0.18,
        3
      ],
      "material": "tuff",
      "size": [
        0.5,
        0.5,
        0.5
      ]
    }
  ],
  "lights": [
    {
      "type": "area",
      "position": [
        0,
        6,
        0
      ],
      "intensity": [
        0.35,
        0.18,
        0.55
      ],
      "radius": 0.8,
      "orbit": {
        "center": [
          0,
          0,
          0
        ],
        "radius": 4,
        "height": 6,
        "speed": 0.7,
        "phase": 0.0
      }
    },
    {
      "type": "spot",
      "position": [
        0,
        4,
        0
      ],
      "direction": [
        0,
        -1,
        0
      ],
      "intensity": [
        0.4,
        0.2,
        0.6
      ],
      "angle": 45,
      "falloff": 2
    },
    {
      "type": "area",
      "position": [
        -3,
        3,
        -2
      ],
      "intensity": [
        0.25,
        0.12,
        0.4
      ],
      "radius": 0.4
    },
    {
      "type": "area",
      "position": [
        3,
        3,
        2
      ],
      "intensity": [
        0.2,
        0.1,
        0.35
      ],
      "radius": 0.3
    }
  ]
}
